setup.py
monarch/__init__.py
monarch/configuration.py
monarch/locks.py
monarch/rules.py
monarch_dnd.egg-info/PKG-INFO
monarch_dnd.egg-info/SOURCES.txt
monarch_dnd.egg-info/dependency_links.txt
monarch_dnd.egg-info/requires.txt
monarch_dnd.egg-info/top_level.txt