Metadata-Version: 1.0
Name: monarch-dnd
Version: 0.1.1
Summary: Monarch is a throttle for task/jobs like push notification, sms or emails.
Home-page: https://github.com/Peppertap/monarch
Author: peppertap
Author-email: backend+monarch@peppertap.com
License: MIT
Keywords: monarch,dnd,DoNotDisturb
Platform: UNKNOWN
